[
  {
    "id": "1",
    "name": "Hamilton Lewis",
    "email": "dui.in@egetlacus.ca",
    "phone": "(294) 840-00eee00"
  },
  {
    "id": "3",
    "name": "Kennedy Lane",
    "email": "mattis.Cras@nonenimMauris.net",
    "phone": "(542) 451-7038"
  },
  {
    "id": "4",
    "name": "Wylie Pope",
    "email": "est@utquamvel.net",
    "phone": "(692) 802-2949"
  },
  {
    "id": "5",
    "name": "Cyrus Jackson",
    "email": "nibh@semsempererat.com",
    "phone": "(501) 472-5218"
  },
  {
    "id": "6",
    "name": "Abbot Franks",
    "email": "scelerisque@magnis.org",
    "phone": "(186) 568-3720"
  },
  {
    "id": "7",
    "name": "Reuben Henry",
    "email": "pharetra.ut@dictum.co.uk",
    "phone": "(715) 598-5792"
  },
  {
    "id": "8",
    "name": "Simon Morton",
    "email": "dui.Fusce.diam@Donec.com",
    "phone": "(233) 738-2360"
  },
  {
    "id": "9",
    "name": "Thomas Lucas",
    "email": "nec@Nulla.com",
    "phone": "(704) 398-7993"
  },
  {
    "id": "10",
    "name": "Alec Howard",
    "email": "Donec.elementum@scelerisquescelerisquedui.net",
    "phone": "(748) 206-2688"
  },
  {
    "id": "8c24546f-7832-4ad6-a3b7-25d704f969ce",
    "name": "Hamilton Lewis",
    "email": "dui.in@egetlacus.ca",
    "phone": "(294) 840-0000"
  },
  {
    "id": "7a9c1367-b509-443f-a34a-76786866d22d",
    "name": "Hamilton Lewis",
    "email": "dui.in@egetlacus.ca",
    "phone": "(294) 840-0000"
  },
  {
    "id": "dcc90ed9-fbff-4296-b8fb-90582d170816",
    "name": "Hamilton Lewis",
    "email": "dui.in@egetlacus.ca",
    "phone": "(294) 840-0000"
  },
  {
    "id": "8a56f5d3-b3ff-45cf-8977-4f81703af986",
    "name": "Hamilton Lewis",
    "email": "dui.in@egetlacus.ca",
    "phone": "(294) 840-8888"
  },
  {
    "id": "918eff16-12a9-4d14-983d-8e1e917fc0c4",
    "name": "Hamilton Lewis",
    "email": "dui.in@egetlacus.ca",
    "phone": "(294) 840-8888u"
  },
  {
    "id": "5ec2f0c1-09bd-4456-bd95-fbb839da0376",
    "name": "Hamilton Lewis",
    "email": "dui.in@egetlacus.ca",
    "phone": "(294) 840-8888"
  },
  {
    "id": "a2638fca-f6db-4afc-8536-f289e4223a4b",
    "name": "Hamilton Lewis",
    "email": "dui.in@egetlacus.ca",
    "phone": "(294) 840-8888"
  },
  {
    "id": "ccca835b-2630-4584-8146-f9b7e164b539",
    "name": "Hamilton Lewis",
    "email": "dui.in@egetlacus.ca",
    "phone": "(294) 840-8888"
  }
]